z3c.evalexception-4.0-py3.11-nspkg.pth
z3c/evalexception/__init__.py
z3c/evalexception/tests.py
z3c.evalexception-4.0.dist-info/LICENSE.txt
z3c.evalexception-4.0.dist-info/METADATA
z3c.evalexception-4.0.dist-info/WHEEL
z3c.evalexception-4.0.dist-info/entry_points.txt
z3c.evalexception-4.0.dist-info/namespace_packages.txt
z3c.evalexception-4.0.dist-info/top_level.txt
z3c.evalexception-4.0.dist-info/zip-safe
z3c.evalexception-4.0.dist-info/RECORD
