Metadata-Version: 2.1
Name: z3c.evalexception
Version: 4.0
Summary: Debugging middlewares for zope.publisher-based web applications
Home-page: https://github.com/zopefoundation/z3c.evalexception
Author: Philipp von Weitershausen
Author-email: philipp@weitershausen.de
License: ZPL 2.1
Classifier: Development Status :: 5 - Production/Stable
Classifier: Environment :: Web Environment
Classifier: Intended Audience :: Developers
Classifier: License :: OSI Approved :: Zope Public License
Classifier: Programming Language :: Python
Classifier: Operating System :: OS Independent
Classifier: Topic :: Internet :: WWW/HTTP
Classifier: Programming Language :: Python
Classifier: Programming Language :: Python :: 3
Classifier: Programming Language :: Python :: 3.7
Classifier: Programming Language :: Python :: 3.8
Classifier: Programming Language :: Python :: 3.9
Classifier: Programming Language :: Python :: 3.10
Classifier: Programming Language :: Python :: 3.11
Classifier: Framework :: Zope :: 3
Classifier: Framework :: Paste
Requires-Python: >=3.7
License-File: LICENSE.txt
Requires-Dist: setuptools
Requires-Dist: Paste
Requires-Dist: zope.security
Provides-Extra: test
Requires-Dist: zope.testrunner ; extra == 'test'
